DFTrans_main.py
df_excel_define.py
df_excel_define_user.py
df_excel_plot.py
df_stock_define.py
git/dftrans/config/img/table_arrow9_transparent_256.png
git/dftrans/config/img/table_arrow9_transparent_64.ico
dftrans-2.0.2.9.dist-info/LICENSE
dftrans-2.0.2.9.dist-info/METADATA
dftrans-2.0.2.9.dist-info/WHEEL
dftrans-2.0.2.9.dist-info/entry_points.txt
dftrans-2.0.2.9.dist-info/top_level.txt
dftrans-2.0.2.9.dist-info/RECORD
