Metadata-Version: 2.1
Name: dftrans
Version: 2.0.2.9
Summary: 用于批量处理excel、sql数据库表、jsonl、csv等数据源的文件，并输出到数据库表或这excel文件
Home-page: https://gitee.com/Frank_583983716/dftrans
Author: Frank Gong
Author-email: 583983716@qq.com
License: BSD
License-File: LICENSE
Requires-Dist: pandas (~=1.5.2)
Requires-Dist: numpy (~=1.24.1)
Requires-Dist: openpyxl
Requires-Dist: argparse
Requires-Dist: pathlib
Requires-Dist: selenium
Requires-Dist: requests
Requires-Dist: xlrd
Requires-Dist: bottle
Requires-Dist: PySimpleGUI (~=4.59.0)
Requires-Dist: chardet
Requires-Dist: nuitka
Requires-Dist: PyQt5
Requires-Dist: pycryptodomex
Requires-Dist: datacompy
Requires-Dist: shortuuid
Requires-Dist: sqlalchemy (==1.4.46)
Requires-Dist: mysql-connector-python
Requires-Dist: ipy
Requires-Dist: pathos
Requires-Dist: pymysql
Requires-Dist: colorlog
Requires-Dist: matplotlib (~=3.7.2)
Requires-Dist: pypinyin
Requires-Dist: pyxlsb
Requires-Dist: jsonlines
Requires-Dist: Jinja2
Requires-Dist: psgspecialelements
